fiduswriter/citation_api_import/__init__.py
fiduswriter/citation_api_import/apps.py
fiduswriter/citation_api_import/urls.py
fiduswriter/citation_api_import/views.py
fiduswriter/citation_api_import/locale/bg/LC_MESSAGES/djangojs.mo
fiduswriter/citation_api_import/locale/bg/LC_MESSAGES/djangojs.po
fiduswriter/citation_api_import/locale/de/LC_MESSAGES/djangojs.mo
fiduswriter/citation_api_import/locale/de/LC_MESSAGES/djangojs.po
fiduswriter/citation_api_import/locale/es/LC_MESSAGES/djangojs.mo
fiduswriter/citation_api_import/locale/es/LC_MESSAGES/djangojs.po
fiduswriter/citation_api_import/locale/fr/LC_MESSAGES/djangojs.mo
fiduswriter/citation_api_import/locale/fr/LC_MESSAGES/djangojs.po
fiduswriter/citation_api_import/locale/it/LC_MESSAGES/djangojs.mo
fiduswriter/citation_api_import/locale/it/LC_MESSAGES/djangojs.po
fiduswriter/citation_api_import/locale/pt_BR/LC_MESSAGES/djangojs.mo
fiduswriter/citation_api_import/locale/pt_BR/LC_MESSAGES/djangojs.po
fiduswriter/citation_api_import/static/css/citation_api_import.css
fiduswriter/citation_api_import/static/js/modules/citation_api_import/crossref.js
fiduswriter/citation_api_import/static/js/modules/citation_api_import/datacite.js
fiduswriter/citation_api_import/static/js/modules/citation_api_import/gesis.js
fiduswriter/citation_api_import/static/js/modules/citation_api_import/index.js
fiduswriter/citation_api_import/static/js/modules/citation_api_import/pubmed.js
fiduswriter/citation_api_import/static/js/modules/citation_api_import/templates.js
fiduswriter/citation_api_import/static/js/modules/citation_api_import/zenon.js
fiduswriter/citation_api_import/static/js/plugins/bibliography_overview/citation_api_import.js
fiduswriter/citation_api_import/static/js/plugins/citation_dialog/citation_api_import.js
fiduswriter/citation_api_import/tests/__init__.py
fiduswriter/citation_api_import/tests/test_citation_api_import.py
fiduswriter_citation_api_import-4.0.1.dist-info/licenses/LICENSE
fiduswriter_citation_api_import-4.0.1.dist-info/METADATA
fiduswriter_citation_api_import-4.0.1.dist-info/WHEEL
fiduswriter_citation_api_import-4.0.1.dist-info/top_level.txt
fiduswriter_citation_api_import-4.0.1.dist-info/RECORD
